pydiablo/__init__.py
pydiablo/char.py
pydiablo/d2data.py
pydiablo/error.py
pydiablo/logger.py
pydiablo/monster.py
pydiablo/data/global/excel/ItemStatCost.txt
pydiablo/data/global/excel/Levels.txt
pydiablo/data/global/excel/MonLvl.txt
pydiablo/data/global/excel/MonProp.txt
pydiablo/data/global/excel/Properties.txt
pydiablo/data/global/excel/SetItems.txt
pydiablo/data/global/excel/Sets.txt
pydiablo/data/global/excel/SuperUniques.txt
pydiablo/data/global/excel/monstats.txt
pydiablo/data/global/excel/monstats2.txt
pydiablo/data/global/excel/monumod.txt
pydiablo/data2/SetItems2.txt
pydiablo/data2/SuperUniques2.txt
pydiablo/data2/animdata.txt
pydiablo-0.0.3.dist-info/LICENSE
pydiablo-0.0.3.dist-info/METADATA
pydiablo-0.0.3.dist-info/WHEEL
pydiablo-0.0.3.dist-info/top_level.txt
pydiablo-0.0.3.dist-info/RECORD
