Metadata-Version: 2.1
Name: pydiablo
Version: 0.0.3
Summary: A collection of Diablo 2 utilities.
Home-page: https://github.com/youbetterdont/pydiablo
Author: youbetterdont
License: UNKNOWN
Platform: UNKNOWN
Classifier: Programming Language :: Python :: 3
Classifier: License :: OSI Approved :: MIT License
Classifier: Operating System :: OS Independent
Requires-Dist: numpy (>=1.15)
